odoo9_addon_mail_log_messages_to_process-9.0.1.0.0-py2.7-nspkg.pth
odoo9_addon_mail_log_messages_to_process-9.0.1.0.0.dist-info/DESCRIPTION.rst
odoo9_addon_mail_log_messages_to_process-9.0.1.0.0.dist-info/METADATA
odoo9_addon_mail_log_messages_to_process-9.0.1.0.0.dist-info/RECORD
odoo9_addon_mail_log_messages_to_process-9.0.1.0.0.dist-info/WHEEL
odoo9_addon_mail_log_messages_to_process-9.0.1.0.0.dist-info/metadata.json
odoo9_addon_mail_log_messages_to_process-9.0.1.0.0.dist-info/namespace_packages.txt
odoo9_addon_mail_log_messages_to_process-9.0.1.0.0.dist-info/top_level.txt
odoo_addons/mail_log_messages_to_process/README.rst
odoo_addons/mail_log_messages_to_process/__init__.py
odoo_addons/mail_log_messages_to_process/__openerp__.py
odoo_addons/mail_log_messages_to_process/models/__init__.py
odoo_addons/mail_log_messages_to_process/models/mail_thread.py
odoo_addons/mail_log_messages_to_process/static/description/icon.png
